html2object/__init__.py
html2object/html2object.py
html2object/html_element.py
tests/__init__.py
tests/test_html2object.py
tests/test_html_element.py
html2object-1.1.0.dist-info/LICENSE
html2object-1.1.0.dist-info/METADATA
html2object-1.1.0.dist-info/WHEEL
html2object-1.1.0.dist-info/top_level.txt
html2object-1.1.0.dist-info/RECORD
