Metadata-Version: 2.1
Name: html2object
Version: 1.1.0
Summary: Tools to handle the CRUD of .html files as objects.
Home-page: https://github.com/boterop/html2object
Author: boterop
Author-email: boterop22@gmail.com
Keywords: html,utils,html_utils,html_element,html_parser,html_writer,html_reader,html_crud,html_object,html_file,html_utils.py,html_element.py,html_parser.py,html_writer.py,html_reader.py,html_crud.py,html_object.py,html_file.py,html2object,html2object.py,html2object.py
Classifier: Development Status :: 5 - Production/Stable
Classifier: Intended Audience :: Developers
Classifier: License :: OSI Approved :: MIT License
Classifier: Programming Language :: Python :: 3
Classifier: Programming Language :: Python :: 3.6
Classifier: Programming Language :: Python :: 3.7
Classifier: Programming Language :: Python :: 3.8
Classifier: Programming Language :: Python :: 3.10
Classifier: Programming Language :: Python :: 3.12
Requires-Python: >=3.6
License-File: LICENSE
